ksd/__init__.py
ksd/ksd.py
ksd-0.1.3.dist-info/LICENSE.txt
ksd-0.1.3.dist-info/METADATA
ksd-0.1.3.dist-info/WHEEL
ksd-0.1.3.dist-info/entry_points.txt
ksd-0.1.3.dist-info/top_level.txt
ksd-0.1.3.dist-info/RECORD
