Metadata-Version: 2.1
Name: ksd
Version: 0.1.3
Summary: Utility for decoding Kubernetes secret resources
Author-email: Joe Jasinski <joe.jasinski@gmail.com>
Project-URL: Homepage, https://github.com/JoeJasinski/ksd
Keywords: kubernetes,kubectl,secrets
Classifier: License :: OSI Approved :: MIT License
Classifier: Programming Language :: Python
Classifier: Programming Language :: Python :: 3
Requires-Python: >=3.7
License-File: LICENSE.txt
Requires-Dist: PyYAML >=5.0
Provides-Extra: tests
Requires-Dist: pytest >=8 ; extra == 'tests'
